raindrop/__init__.py
raindrop/cache.py
raindrop/cli.py
raindrop/commands/__init__.py
raindrop/commands/alerts.py
raindrop/commands/aqi.py
raindrop/commands/astro.py
raindrop/commands/clothing.py
raindrop/commands/compare.py
raindrop/commands/completions.py
raindrop/commands/config.py
raindrop/commands/current.py
raindrop/commands/daily.py
raindrop/commands/dashboard.py
raindrop/commands/discussion.py
raindrop/commands/favorites.py
raindrop/commands/history.py
raindrop/commands/hourly.py
raindrop/commands/marine.py
raindrop/commands/precip.py
raindrop/commands/route.py
raindrop/utils/__init__.py
raindrop/utils/astro.py
raindrop/utils/formatting.py
raindrop/utils/weather.py
open_meteo.py
settings.py
rdrop-0.1.0.dist-info/METADATA
rdrop-0.1.0.dist-info/WHEEL
rdrop-0.1.0.dist-info/entry_points.txt
rdrop-0.1.0.dist-info/RECORD
