Metadata-Version: 2.4
Name: rdrop
Version: 0.1.0
Summary: A beautiful, feature-rich weather CLI for your terminal
Project-URL: Homepage, https://github.com/binarydoubling/raindrop
Project-URL: Repository, https://github.com/binarydoubling/raindrop
Project-URL: Issues, https://github.com/binarydoubling/raindrop/issues
Author: binarydoubling
License-Expression: MIT
Keywords: cli,forecast,sparklines,terminal,tui,weather
Classifier: Development Status :: 4 - Beta
Classifier: Environment :: Console
Classifier: Intended Audience :: Developers
Classifier: Intended Audience :: End Users/Desktop
Classifier: License :: OSI Approved :: MIT License
Classifier: Operating System :: OS Independent
Classifier: Programming Language :: Python :: 3
Classifier: Programming Language :: Python :: 3.12
Classifier: Programming Language :: Python :: 3.13
Classifier: Topic :: Utilities
Requires-Python: >=3.12
Requires-Dist: click>=8.3.1
Requires-Dist: rich>=14.2.0
